file_tag_parser/__init__.py
file_tag_parser/io/__init__.py
file_tag_parser/tags/__init__.py
file_tag_parser/tags/file_tag_parser.py
file_tag_parser/tags/json_format_constants.py
file_tag_parser-0.2.5.3.dist-info/licenses/LICENSE
file_tag_parser-0.2.5.3.dist-info/METADATA
file_tag_parser-0.2.5.3.dist-info/WHEEL
file_tag_parser-0.2.5.3.dist-info/top_level.txt
file_tag_parser-0.2.5.3.dist-info/RECORD
