Metadata-Version: 2.4
Name: file-tag-parser
Version: 0.2.5.3
Summary: A tag-based filename parser for imaging data.
Author-email: Rob F Cooper <robert.cooper@marquette.edu>
License-Expression: Apache-2.0
Project-URL: Homepage, https://github.com/OCVL/file-tag-parser
Classifier: Programming Language :: Python :: 3
Classifier: Operating System :: OS Independent
Requires-Python: >=3.9
License-File: LICENSE
Requires-Dist: pandas>=2.0
Requires-Dist: parse>=1.2.0
Requires-Dist: parse-type>=0.6.4
Dynamic: license-file
